sigma/__init__.py
sigma/_base_client.py
sigma/_client.py
sigma/_compat.py
sigma/_constants.py
sigma/_exceptions.py
sigma/_files.py
sigma/_models.py
sigma/_qs.py
sigma/_resource.py
sigma/_response.py
sigma/_streaming.py
sigma/_types.py
sigma/_version.py
sigma/py.typed
sigma/_utils/__init__.py
sigma/_utils/_logs.py
sigma/_utils/_proxy.py
sigma/_utils/_reflection.py
sigma/_utils/_resources_proxy.py
sigma/_utils/_streams.py
sigma/_utils/_sync.py
sigma/_utils/_transform.py
sigma/_utils/_typing.py
sigma/_utils/_utils.py
sigma/lib/.keep
sigma/resources/__init__.py
sigma/resources/trading.py
sigma/resources/account/__init__.py
sigma/resources/account/account.py
sigma/resources/account/userdata.py
sigma/resources/market/__init__.py
sigma/resources/market/instrument.py
sigma/resources/market/kline.py
sigma/resources/market/market.py
sigma/resources/market/order_book.py
sigma/resources/market/ticker.py
sigma/resources/portfolio/__init__.py
sigma/resources/portfolio/balance.py
sigma/resources/portfolio/credit.py
sigma/resources/portfolio/open_position.py
sigma/resources/portfolio/portfolio.py
sigma/types/__init__.py
sigma/types/order.py
sigma/types/trading_list_response.py
sigma/types/trading_submit_params.py
sigma/types/account/__init__.py
sigma/types/account/user_data.py
sigma/types/market/__init__.py
sigma/types/market/instrument.py
sigma/types/market/kline.py
sigma/types/market/order_book.py
sigma/types/market/ticker.py
sigma/types/portfolio/__init__.py
sigma/types/portfolio/balance.py
sigma/types/portfolio/credit.py
sigma/types/portfolio/open_position.py
sigma/types/portfolio/portfolio.py
sigma_sdk-0.7.0.dist-info/METADATA
sigma_sdk-0.7.0.dist-info/WHEEL
sigma_sdk-0.7.0.dist-info/licenses/LICENSE
sigma_sdk-0.7.0.dist-info/RECORD
